{
  "region": "CA",
  "orders": [
    {
      "orderType": "pnp-only",
      "customer": {
        "name": "Test Customer Langley 1",
        "email": "test-langley-1@example.com",
        "address": "200 Granville Street",
        "city": "Vancouver",
        "province": "BC",
        "postalCode": "V6C 1S4"
      },
      "lineItems": [
        {
          "sku": "14019-0-0-7RL-1",
          "quantity": 5,
          "pickType": "Pick and Pack"
        },
        {
          "sku": "46K49-0-0U-0-S-1-102-D",
          "quantity": 2,
          "pickType": "Pick and Pack"
        },
        {
          "sku": "3+2R01-0-0-701-R",
          "quantity": 4,
          "pickType": "Pick and Pack"
        },
        {
          "sku": "GIA-6900-HW-30000000",
          "quantity": 10,
          "pickType": "Pick and Pack"
        },
        {
          "sku": "2069-L-00-300-S-R",
          "quantity": 2,
          "pickType": "Pick and Pack"
        },
        {
          "sku": "3287-0-00-300",
          "quantity": 2,
          "pickType": "Pick and Pack"
        },
        {
          "sku": "3+3019-0-L-701-R",
          "quantity": 2,
          "pickType": "Pick and Pack"
        },
        {
          "sku": "2+3058-2-00-300",
          "quantity": 1,
          "pickType": "Pick and Pack"
        },
        {
          "sku": "2+2+2L01-0-0-710-R",
          "quantity": 2,
          "pickType": "Pick and Pack"
        },
        {
          "sku": "2+1219-L-0-700-R",
          "quantity": 1,
          "pickType": "Pick and Pack"
        }
      ]
    },
    {
      "orderType": "pnp-only",
      "customer": {
        "name": "Test Customer Windsor 1",
        "email": "test-windsor-1@example.com",
        "address": "350 City Hall Square West",
        "city": "Windsor",
        "province": "ON",
        "postalCode": "N9A 6S1"
      },
      "lineItems": [
        {
          "sku": "11008-E-1-7LL",
          "quantity": 2,
          "pickType": "Pick and Pack"
        },
        {
          "sku": "32003-303",
          "quantity": 1,
          "pickType": "Pick and Pack"
        }
      ]
    },
    {
      "orderType": "pnp-only",
      "customer": {
        "name": "Test Customer Windsor 2",
        "email": "test-windsor-2@example.com",
        "address": "1155 Lauzon Road",
        "city": "Windsor",
        "province": "ON",
        "postalCode": "N8S 3N1"
      },
      "lineItems": [
        {
          "sku": "70048-E-00-300-S",
          "quantity": 12,
          "pickType": "Pick and Pack"
        },
        {
          "sku": "46F49-0-0U-0-S-2-102-D",
          "quantity": 2,
          "pickType": "Pick and Pack"
        },
        {
          "sku": "30022-308-R",
          "quantity": 6,
          "pickType": "Pick and Pack"
        },
        {
          "sku": "12044-0-00-300-S",
          "quantity": 1,
          "pickType": "Pick and Pack"
        },
        {
          "sku": "71044-0-00-301",
          "quantity": 2,
          "pickType": "Pick and Pack"
        },
        {
          "sku": "2053-R-00-300-S",
          "quantity": 3,
          "pickType": "Pick and Pack"
        },
        {
          "sku": "1+2R01-0-L-700-R",
          "quantity": 2,
          "pickType": "Pick and Pack"
        }
      ]
    },
    {
      "orderType": "mixed",
      "customer": {
        "name": "Test Customer Langley 2",
        "email": "test-langley-2@example.com",
        "address": "13737 96 Avenue",
        "city": "Surrey",
        "province": "BC",
        "postalCode": "V3V 0C6"
      },
      "lineItems": [
        {
          "sku": "3526-102-R",
          "quantity": 20,
          "pickType": "Regular"
        },
        {
          "sku": "3+2081-410-R",
          "quantity": 2,
          "pickType": "Regular"
        },
        {
          "sku": "3246-301-R",
          "quantity": 5,
          "pickType": "Regular"
        },
        {
          "sku": "10033-0-00-610",
          "quantity": 4,
          "pickType": "Regular"
        },
        {
          "sku": "2+3+2077-0-L-900",
          "quantity": 1,
          "pickType": "Regular"
        },
        {
          "sku": "2+2119-201-D",
          "quantity": 2,
          "pickType": "Regular"
        },
        {
          "sku": "34039-1-117-9x12C",
          "quantity": 1,
          "pickType": "Regular"
        },
        {
          "sku": "1+2L73-0-R-711-R",
          "quantity": 5,
          "pickType": "Pick and Pack"
        },
        {
          "sku": "2+2+2L73-0-R-701-R",
          "quantity": 3,
          "pickType": "Pick and Pack"
        }
      ]
    },
    {
      "orderType": "regular-only",
      "customer": {
        "name": "Test Customer Royalmount 2",
        "email": "test-royalmount-2@example.com",
        "address": "1250 Boulevard René-Lévesque Ouest",
        "city": "Montreal",
        "province": "QC",
        "postalCode": "H3B 4W8"
      },
      "lineItems": [
        {
          "sku": "2244-301-D",
          "quantity": 2,
          "pickType": "Regular"
        },
        {
          "sku": "3439-111-D",
          "quantity": 2,
          "pickType": "Regular"
        },
        {
          "sku": "2+1050-L-00-300-S",
          "quantity": 2,
          "pickType": "Regular"
        },
        {
          "sku": "2L47-0-00-300-R",
          "quantity": 1,
          "pickType": "Regular"
        },
        {
          "sku": "2+3+2046-R-00-300-R",
          "quantity": 5,
          "pickType": "Regular"
        }
      ]
    },
    {
      "orderType": "mixed",
      "customer": {
        "name": "Test Customer Royalmount 1",
        "email": "test-royalmount-1@example.com",
        "address": "275 Rue Notre-Dame Est",
        "city": "Montreal",
        "province": "QC",
        "postalCode": "H2Y 1C6"
      },
      "lineItems": [
        {
          "sku": "1+2101-202",
          "quantity": 2,
          "pickType": "Regular"
        },
        {
          "sku": "2+1271-2A1-R",
          "quantity": 1,
          "pickType": "Regular"
        },
        {
          "sku": "32008-308-D",
          "quantity": 1,
          "pickType": "Regular"
        },
        {
          "sku": "4278-0-03-610-R",
          "quantity": 2,
          "pickType": "Regular"
        },
        {
          "sku": "3+3L87-0-00-300-S",
          "quantity": 6,
          "pickType": "Pick and Pack"
        },
        {
          "sku": "1+2+1L73-0-0-710-R",
          "quantity": 1,
          "pickType": "Pick and Pack"
        },
        {
          "sku": "1+2250-0-00-300",
          "quantity": 5,
          "pickType": "Pick and Pack"
        },
        {
          "sku": "GIA-6900-HW-30000000-R",
          "quantity": 1,
          "pickType": "Pick and Pack"
        }
      ]
    },
    {
      "orderType": "regular-only",
      "customer": {
        "name": "Test Customer Royalmount 1",
        "email": "test-royalmount-1@example.com",
        "address": "275 Rue Notre-Dame Est",
        "city": "Montreal",
        "province": "QC",
        "postalCode": "H2Y 1C6"
      },
      "lineItems": [
        {
          "sku": "3333-112-D",
          "quantity": 2,
          "pickType": "Regular"
        },
        {
          "sku": "2+2+2320-201",
          "quantity": 1,
          "pickType": "Regular"
        },
        {
          "sku": "2+2+2078-0-R-800",
          "quantity": 1,
          "pickType": "Regular"
        },
        {
          "sku": "14008-201",
          "quantity": 1,
          "pickType": "Regular"
        },
        {
          "sku": "2+3+2219-2A1",
          "quantity": 3,
          "pickType": "Regular"
        }
      ]
    },
    {
      "orderType": "mixed",
      "customer": {
        "name": "Test Customer Windsor 1",
        "email": "test-windsor-1@example.com",
        "address": "350 City Hall Square West",
        "city": "Windsor",
        "province": "ON",
        "postalCode": "N9A 6S1"
      },
      "lineItems": [
        {
          "sku": "34026-1-67-9x12C",
          "quantity": 1,
          "pickType": "Regular"
        },
        {
          "sku": "2R40-301",
          "quantity": 3,
          "pickType": "Regular"
        },
        {
          "sku": "3+2R41-0-00-300-R",
          "quantity": 2,
          "pickType": "Regular"
        },
        {
          "sku": "1+2+1073-0-2-700-R",
          "quantity": 2,
          "pickType": "Pick and Pack"
        },
        {
          "sku": "20077-208",
          "quantity": 1,
          "pickType": "Pick and Pack"
        },
        {
          "sku": "SP-01-600-34-001",
          "quantity": 1,
          "pickType": "Pick and Pack"
        },
        {
          "sku": "2+2+2073-0-R-701-R",
          "quantity": 2,
          "pickType": "Pick and Pack"
        }
      ]
    },
    {
      "orderType": "pnp-only",
      "customer": {
        "name": "Test Customer Langley 1",
        "email": "test-langley-1@example.com",
        "address": "200 Granville Street",
        "city": "Vancouver",
        "province": "BC",
        "postalCode": "V6C 1S4"
      },
      "lineItems": [
        {
          "sku": "3+2R08-0-0-701-R",
          "quantity": 12,
          "pickType": "Pick and Pack"
        },
        {
          "sku": "2+3L16-0-R-701-R",
          "quantity": 2,
          "pickType": "Pick and Pack"
        },
        {
          "sku": "71048-0-00-300",
          "quantity": 2,
          "pickType": "Pick and Pack"
        },
        {
          "sku": "4219-R-0-700",
          "quantity": 3,
          "pickType": "Pick and Pack"
        },
        {
          "sku": "20028-106",
          "quantity": 1,
          "pickType": "Pick and Pack"
        },
        {
          "sku": "72056-0-00-302-R",
          "quantity": 1,
          "pickType": "Pick and Pack"
        }
      ]
    },
    {
      "orderType": "mixed",
      "customer": {
        "name": "Test Customer Windsor 3",
        "email": "test-windsor-3@example.com",
        "address": "3000 Dougall Avenue",
        "city": "Windsor",
        "province": "ON",
        "postalCode": "N9E 1S3"
      },
      "lineItems": [
        {
          "sku": "1+2089-0-00-300-S",
          "quantity": 2,
          "pickType": "Regular"
        },
        {
          "sku": "11019-0-0-703-D",
          "quantity": 1,
          "pickType": "Regular"
        },
        {
          "sku": "34004-1-56-9x12F",
          "quantity": 1,
          "pickType": "Regular"
        },
        {
          "sku": "46Q74-R-UU-N-S-2-100-R",
          "quantity": 1,
          "pickType": "Regular"
        },
        {
          "sku": "4276-0-00-501-R",
          "quantity": 1,
          "pickType": "Regular"
        },
        {
          "sku": "34023-1-73-9x12C-D",
          "quantity": 9,
          "pickType": "Regular"
        },
        {
          "sku": "2+3228-101",
          "quantity": 1,
          "pickType": "Regular"
        },
        {
          "sku": "2+3019-0-00-501",
          "quantity": 2,
          "pickType": "Regular"
        },
        {
          "sku": "3+3273-0-03-610",
          "quantity": 1,
          "pickType": "Regular"
        },
        {
          "sku": "10076-2A0-R",
          "quantity": 8,
          "pickType": "Regular"
        },
        {
          "sku": "3019-L-0-700-R",
          "quantity": 1,
          "pickType": "Pick and Pack"
        },
        {
          "sku": "2+1077-0-L-800-D",
          "quantity": 1,
          "pickType": "Regular"
        },
        {
          "sku": "2+3074-0-0-900-R",
          "quantity": 1,
          "pickType": "Regular"
        },
        {
          "sku": "46F73-S-UU-N-E-4-100-R",
          "quantity": 2,
          "pickType": "Regular"
        },
        {
          "sku": "3+3276-0-0-800",
          "quantity": 2,
          "pickType": "Regular"
        },
        {
          "sku": "2+3+2472-202",
          "quantity": 1,
          "pickType": "Regular"
        },
        {
          "sku": "2+1019-0-R-700",
          "quantity": 1,
          "pickType": "Pick and Pack"
        },
        {
          "sku": "3+3R01-0-00-501",
          "quantity": 2,
          "pickType": "Regular"
        },
        {
          "sku": "2+3+2032-102",
          "quantity": 1,
          "pickType": "Regular"
        },
        {
          "sku": "2+2241-301-D",
          "quantity": 1,
          "pickType": "Regular"
        }
      ]
    },
    {
      "orderType": "pnp-only",
      "customer": {
        "name": "Test Customer Royalmount 3",
        "email": "test-royalmount-3@example.com",
        "address": "1055 Rue Saint-Laurent Ouest",
        "city": "Longueuil",
        "province": "QC",
        "postalCode": "J4K 1C7"
      },
      "lineItems": [
        {
          "sku": "2R19-L-0-700-R",
          "quantity": 2,
          "pickType": "Pick and Pack"
        },
        {
          "sku": "3+3L01-0-0-711-R",
          "quantity": 1,
          "pickType": "Pick and Pack"
        },
        {
          "sku": "70069-0-00-300-S",
          "quantity": 1,
          "pickType": "Pick and Pack"
        }
      ]
    },
    {
      "orderType": "regular-only",
      "customer": {
        "name": "Test Customer Windsor 3",
        "email": "test-windsor-3@example.com",
        "address": "3000 Dougall Avenue",
        "city": "Windsor",
        "province": "ON",
        "postalCode": "N9E 1S3"
      },
      "lineItems": [
        {
          "sku": "3L36-0-SS-610",
          "quantity": 2,
          "pickType": "Regular"
        },
        {
          "sku": "2+1139-112-R",
          "quantity": 1,
          "pickType": "Regular"
        },
        {
          "sku": "11083-402-R",
          "quantity": 7,
          "pickType": "Regular"
        }
      ]
    },
    {
      "orderType": "pnp-only",
      "customer": {
        "name": "Test Customer Langley 3",
        "email": "test-langley-3@example.com",
        "address": "4949 Canada Way",
        "city": "Burnaby",
        "province": "BC",
        "postalCode": "V5G 1M2"
      },
      "lineItems": [
        {
          "sku": "46Q75-0-0U-0-E-2-102-D",
          "quantity": 2,
          "pickType": "Pick and Pack"
        },
        {
          "sku": "3+2201-0-0-711",
          "quantity": 10,
          "pickType": "Pick and Pack"
        },
        {
          "sku": "20017-208",
          "quantity": 10,
          "pickType": "Pick and Pack"
        },
        {
          "sku": "3+2073-0-0-700-R",
          "quantity": 2,
          "pickType": "Pick and Pack"
        },
        {
          "sku": "1R77-0-0-800",
          "quantity": 2,
          "pickType": "Pick and Pack"
        },
        {
          "sku": "U26000-00-422-D",
          "quantity": 2,
          "pickType": "Pick and Pack"
        },
        {
          "sku": "3201-L-0-700",
          "quantity": 2,
          "pickType": "Pick and Pack"
        },
        {
          "sku": "4L19-L-0-710-R",
          "quantity": 20,
          "pickType": "Pick and Pack"
        }
      ]
    },
    {
      "orderType": "mixed",
      "customer": {
        "name": "Test Customer Windsor 1",
        "email": "test-windsor-1@example.com",
        "address": "350 City Hall Square West",
        "city": "Windsor",
        "province": "ON",
        "postalCode": "N9A 6S1"
      },
      "lineItems": [
        {
          "sku": "44022-0-49-500-D",
          "quantity": 2,
          "pickType": "Regular"
        },
        {
          "sku": "71089-0-00-302",
          "quantity": 2,
          "pickType": "Pick and Pack"
        }
      ]
    },
    {
      "orderType": "mixed",
      "customer": {
        "name": "Test Customer Royalmount 1",
        "email": "test-royalmount-1@example.com",
        "address": "275 Rue Notre-Dame Est",
        "city": "Montreal",
        "province": "QC",
        "postalCode": "H2Y 1C6"
      },
      "lineItems": [
        {
          "sku": "3132-112-D",
          "quantity": 2,
          "pickType": "Regular"
        },
        {
          "sku": "2+3+2L43-301-D",
          "quantity": 5,
          "pickType": "Regular"
        },
        {
          "sku": "2089-2-00-300-S-D",
          "quantity": 1,
          "pickType": "Pick and Pack"
        },
        {
          "sku": "4R19-0-0-711",
          "quantity": 5,
          "pickType": "Pick and Pack"
        }
      ]
    },
    {
      "orderType": "regular-only",
      "customer": {
        "name": "Test Customer Royalmount 2",
        "email": "test-royalmount-2@example.com",
        "address": "1250 Boulevard René-Lévesque Ouest",
        "city": "Montreal",
        "province": "QC",
        "postalCode": "H3B 4W8"
      },
      "lineItems": [
        {
          "sku": "2+3277-0-SS-610-D",
          "quantity": 2,
          "pickType": "Regular"
        },
        {
          "sku": "10034-0-00-610-D",
          "quantity": 4,
          "pickType": "Regular"
        },
        {
          "sku": "2+3134-111-R",
          "quantity": 1,
          "pickType": "Regular"
        }
      ]
    },
    {
      "orderType": "mixed",
      "customer": {
        "name": "Test Customer Windsor 2",
        "email": "test-windsor-2@example.com",
        "address": "1155 Lauzon Road",
        "city": "Windsor",
        "province": "ON",
        "postalCode": "N8S 3N1"
      },
      "lineItems": [
        {
          "sku": "2OR76-0-02-610",
          "quantity": 7,
          "pickType": "Regular"
        },
        {
          "sku": "11047-E-00-300-S",
          "quantity": 1,
          "pickType": "Pick and Pack"
        }
      ]
    },
    {
      "orderType": "pnp-only",
      "customer": {
        "name": "Test Customer Windsor 3",
        "email": "test-windsor-3@example.com",
        "address": "3000 Dougall Avenue",
        "city": "Windsor",
        "province": "ON",
        "postalCode": "N9E 1S3"
      },
      "lineItems": [
        {
          "sku": "3075-2-0-900",
          "quantity": 3,
          "pickType": "Pick and Pack"
        },
        {
          "sku": "SP-01-600-76-004",
          "quantity": 1,
          "pickType": "Pick and Pack"
        },
        {
          "sku": "30027-1-30-18x18K-R",
          "quantity": 2,
          "pickType": "Pick and Pack"
        },
        {
          "sku": "2+3+2R16-0-L-700",
          "quantity": 4,
          "pickType": "Pick and Pack"
        },
        {
          "sku": "32032-1-00-3x1-R",
          "quantity": 4,
          "pickType": "Pick and Pack"
        },
        {
          "sku": "3L19-0-0-700-R",
          "quantity": 2,
          "pickType": "Pick and Pack"
        },
        {
          "sku": "70057-0-00-301-S-R",
          "quantity": 2,
          "pickType": "Pick and Pack"
        }
      ]
    },
    {
      "orderType": "regular-only",
      "customer": {
        "name": "Test Customer Royalmount 2",
        "email": "test-royalmount-2@example.com",
        "address": "1250 Boulevard René-Lévesque Ouest",
        "city": "Montreal",
        "province": "QC",
        "postalCode": "H3B 4W8"
      },
      "lineItems": [
        {
          "sku": "46F49-S-UU-N-E-2-100-D",
          "quantity": 2,
          "pickType": "Regular"
        },
        {
          "sku": "2+3048-R-00-300",
          "quantity": 1,
          "pickType": "Regular"
        },
        {
          "sku": "2277-0-0-800-R",
          "quantity": 1,
          "pickType": "Regular"
        }
      ]
    },
    {
      "orderType": "regular-only",
      "customer": {
        "name": "Test Customer Langley 1",
        "email": "test-langley-1@example.com",
        "address": "200 Granville Street",
        "city": "Vancouver",
        "province": "BC",
        "postalCode": "V6C 1S4"
      },
      "lineItems": [
        {
          "sku": "72044-0-00-300",
          "quantity": 2,
          "pickType": "Regular"
        },
        {
          "sku": "2+3277-R-0-800",
          "quantity": 9,
          "pickType": "Regular"
        },
        {
          "sku": "2+3+2118-202-R",
          "quantity": 2,
          "pickType": "Regular"
        },
        {
          "sku": "3+2074-0-R-900-D",
          "quantity": 2,
          "pickType": "Regular"
        }
      ]
    }
  ]
}
