{
  "region": "CA",
  "orders": [
    {
      "orderType": "pnp-only",
      "customer": {
        "name": "Test Customer Royalmount 1",
        "email": "test-royalmount-1@example.com",
        "address": "275 Rue Notre-Dame Est",
        "city": "Montreal",
        "province": "QC",
        "postalCode": "H2Y 1C6"
      },
      "lineItems": [
        {
          "sku": "1+2L73-0-0-700",
          "quantity": 1,
          "pickType": "Pick and Pack"
        },
        {
          "sku": "30003-301-R",
          "quantity": 2,
          "pickType": "Pick and Pack"
        },
        {
          "sku": "32068-201",
          "quantity": 1,
          "pickType": "Pick and Pack"
        }
      ]
    },
    {
      "orderType": "regular-only",
      "customer": {
        "name": "Test Customer Windsor 1",
        "email": "test-windsor-1@example.com",
        "address": "350 City Hall Square West",
        "city": "Windsor",
        "province": "ON",
        "postalCode": "N9A 6S1"
      },
      "lineItems": [
        {
          "sku": "2+3+2R89-0-00-300-R",
          "quantity": 19,
          "pickType": "Regular"
        }
      ]
    },
    {
      "orderType": "pnp-only",
      "customer": {
        "name": "Test Customer Royalmount 3",
        "email": "test-royalmount-3@example.com",
        "address": "1055 Rue Saint-Laurent Ouest",
        "city": "Longueuil",
        "province": "QC",
        "postalCode": "J4K 1C7"
      },
      "lineItems": [
        {
          "sku": "2+1058-0-00-300-S-D",
          "quantity": 2,
          "pickType": "Pick and Pack"
        },
        {
          "sku": "46K73-0-0U-0-P-3-102",
          "quantity": 9,
          "pickType": "Pick and Pack"
        },
        {
          "sku": "11008-503-1",
          "quantity": 5,
          "pickType": "Pick and Pack"
        },
        {
          "sku": "72042-301-R",
          "quantity": 6,
          "pickType": "Pick and Pack"
        }
      ]
    },
    {
      "orderType": "mixed",
      "customer": {
        "name": "Test Customer Royalmount 3",
        "email": "test-royalmount-3@example.com",
        "address": "1055 Rue Saint-Laurent Ouest",
        "city": "Longueuil",
        "province": "QC",
        "postalCode": "J4K 1C7"
      },
      "lineItems": [
        {
          "sku": "1+2+1249-0-0-900",
          "quantity": 2,
          "pickType": "Regular"
        },
        {
          "sku": "1124-102-R",
          "quantity": 2,
          "pickType": "Regular"
        },
        {
          "sku": "3+2L19-0-0-700",
          "quantity": 1,
          "pickType": "Pick and Pack"
        },
        {
          "sku": "30018-367K",
          "quantity": 2,
          "pickType": "Pick and Pack"
        },
        {
          "sku": "3052-R-00-300-S",
          "quantity": 1,
          "pickType": "Pick and Pack"
        }
      ]
    },
    {
      "orderType": "mixed",
      "customer": {
        "name": "Test Customer Royalmount 3",
        "email": "test-royalmount-3@example.com",
        "address": "1055 Rue Saint-Laurent Ouest",
        "city": "Longueuil",
        "province": "QC",
        "postalCode": "J4K 1C7"
      },
      "lineItems": [
        {
          "sku": "3+3278-0-SS-610",
          "quantity": 7,
          "pickType": "Regular"
        },
        {
          "sku": "2+1L45-301",
          "quantity": 3,
          "pickType": "Regular"
        },
        {
          "sku": "2+3534-112-D",
          "quantity": 2,
          "pickType": "Regular"
        },
        {
          "sku": "1+2R48-0-00-300",
          "quantity": 2,
          "pickType": "Regular"
        },
        {
          "sku": "46F75-R-UU-S-P-1-100",
          "quantity": 1,
          "pickType": "Regular"
        },
        {
          "sku": "4216-2-0-710",
          "quantity": 1,
          "pickType": "Pick and Pack"
        },
        {
          "sku": "20033-113",
          "quantity": 1,
          "pickType": "Pick and Pack"
        },
        {
          "sku": "2040-L-00-300-S",
          "quantity": 1,
          "pickType": "Pick and Pack"
        },
        {
          "sku": "3049-2-0-800",
          "quantity": 1,
          "pickType": "Pick and Pack"
        },
        {
          "sku": "25000-201",
          "quantity": 2,
          "pickType": "Pick and Pack"
        }
      ]
    },
    {
      "orderType": "pnp-only",
      "customer": {
        "name": "Test Customer Royalmount 3",
        "email": "test-royalmount-3@example.com",
        "address": "1055 Rue Saint-Laurent Ouest",
        "city": "Longueuil",
        "province": "QC",
        "postalCode": "J4K 1C7"
      },
      "lineItems": [
        {
          "sku": "4L73-0-0-700",
          "quantity": 2,
          "pickType": "Pick and Pack"
        },
        {
          "sku": "11L44-E-00-300-S",
          "quantity": 1,
          "pickType": "Pick and Pack"
        },
        {
          "sku": "20078-209-D",
          "quantity": 1,
          "pickType": "Pick and Pack"
        },
        {
          "sku": "4057-2-00-300-S-D",
          "quantity": 1,
          "pickType": "Pick and Pack"
        },
        {
          "sku": "20017-501",
          "quantity": 8,
          "pickType": "Pick and Pack"
        },
        {
          "sku": "70069-0-00-301",
          "quantity": 8,
          "pickType": "Pick and Pack"
        },
        {
          "sku": "72077-0-00-801-D",
          "quantity": 4,
          "pickType": "Pick and Pack"
        }
      ]
    },
    {
      "orderType": "regular-only",
      "customer": {
        "name": "Test Customer Windsor 3",
        "email": "test-windsor-3@example.com",
        "address": "3000 Dougall Avenue",
        "city": "Windsor",
        "province": "ON",
        "postalCode": "N9E 1S3"
      },
      "lineItems": [
        {
          "sku": "46Q74-S-UU-N-S-2-100-R",
          "quantity": 4,
          "pickType": "Regular"
        }
      ]
    },
    {
      "orderType": "pnp-only",
      "customer": {
        "name": "Test Customer Langley 2",
        "email": "test-langley-2@example.com",
        "address": "13737 96 Avenue",
        "city": "Surrey",
        "province": "BC",
        "postalCode": "V3V 0C6"
      },
      "lineItems": [
        {
          "sku": "2+3L73-0-R-701-R",
          "quantity": 10,
          "pickType": "Pick and Pack"
        }
      ]
    },
    {
      "orderType": "regular-only",
      "customer": {
        "name": "Test Customer Windsor 1",
        "email": "test-windsor-1@example.com",
        "address": "350 City Hall Square West",
        "city": "Windsor",
        "province": "ON",
        "postalCode": "N9A 6S1"
      },
      "lineItems": [
        {
          "sku": "2+3331-112",
          "quantity": 2,
          "pickType": "Regular"
        },
        {
          "sku": "2+3L87-0-00-300-D",
          "quantity": 2,
          "pickType": "Regular"
        },
        {
          "sku": "42025-102-1-D",
          "quantity": 4,
          "pickType": "Regular"
        },
        {
          "sku": "2+3137-111-D",
          "quantity": 6,
          "pickType": "Regular"
        },
        {
          "sku": "33002-302-D",
          "quantity": 3,
          "pickType": "Regular"
        },
        {
          "sku": "1+2257-0-00-300-R",
          "quantity": 1,
          "pickType": "Regular"
        },
        {
          "sku": "42024-102-1",
          "quantity": 1,
          "pickType": "Regular"
        },
        {
          "sku": "4R44-0-00-300",
          "quantity": 5,
          "pickType": "Regular"
        },
        {
          "sku": "2247-301",
          "quantity": 10,
          "pickType": "Regular"
        },
        {
          "sku": "42024-101-2x2-R",
          "quantity": 1,
          "pickType": "Regular"
        },
        {
          "sku": "1+2287-0-00-300-S",
          "quantity": 8,
          "pickType": "Regular"
        },
        {
          "sku": "42025-101-1-R",
          "quantity": 2,
          "pickType": "Regular"
        },
        {
          "sku": "42024-101-4x2-R",
          "quantity": 2,
          "pickType": "Regular"
        },
        {
          "sku": "1L50-301",
          "quantity": 1,
          "pickType": "Regular"
        },
        {
          "sku": "3L87-0-00-300",
          "quantity": 2,
          "pickType": "Regular"
        },
        {
          "sku": "2R87-0-00-300-S-D",
          "quantity": 1,
          "pickType": "Regular"
        }
      ]
    },
    {
      "orderType": "regular-only",
      "customer": {
        "name": "Test Customer Royalmount 1",
        "email": "test-royalmount-1@example.com",
        "address": "275 Rue Notre-Dame Est",
        "city": "Montreal",
        "province": "QC",
        "postalCode": "H2Y 1C6"
      },
      "lineItems": [
        {
          "sku": "2+1120-202",
          "quantity": 4,
          "pickType": "Regular"
        },
        {
          "sku": "3L87-0-00-300",
          "quantity": 2,
          "pickType": "Regular"
        },
        {
          "sku": "2+1L50-0-00-300-R",
          "quantity": 8,
          "pickType": "Regular"
        },
        {
          "sku": "2+2+2057-L-00-300-S",
          "quantity": 2,
          "pickType": "Regular"
        },
        {
          "sku": "2+2L08-0-00-5A1",
          "quantity": 5,
          "pickType": "Regular"
        },
        {
          "sku": "2+3041-301-R",
          "quantity": 2,
          "pickType": "Regular"
        },
        {
          "sku": "13071-502",
          "quantity": 2,
          "pickType": "Regular"
        },
        {
          "sku": "2+2+2L41-301-D",
          "quantity": 4,
          "pickType": "Regular"
        },
        {
          "sku": "2+2046-2-00-300-S",
          "quantity": 1,
          "pickType": "Regular"
        },
        {
          "sku": "2+3073-2A1-D",
          "quantity": 2,
          "pickType": "Regular"
        },
        {
          "sku": "1+2319-202",
          "quantity": 1,
          "pickType": "Regular"
        },
        {
          "sku": "3276-2-0-800-D",
          "quantity": 1,
          "pickType": "Regular"
        }
      ]
    },
    {
      "orderType": "regular-only",
      "customer": {
        "name": "Test Customer Langley 1",
        "email": "test-langley-1@example.com",
        "address": "200 Granville Street",
        "city": "Vancouver",
        "province": "BC",
        "postalCode": "V6C 1S4"
      },
      "lineItems": [
        {
          "sku": "1+3069-0-SS-610-D",
          "quantity": 2,
          "pickType": "Regular"
        }
      ]
    },
    {
      "orderType": "mixed",
      "customer": {
        "name": "Test Customer Langley 1",
        "email": "test-langley-1@example.com",
        "address": "200 Granville Street",
        "city": "Vancouver",
        "province": "BC",
        "postalCode": "V6C 1S4"
      },
      "lineItems": [
        {
          "sku": "3+3078-0-00-501-R",
          "quantity": 3,
          "pickType": "Regular"
        },
        {
          "sku": "10030-100-R",
          "quantity": 2,
          "pickType": "Regular"
        },
        {
          "sku": "3+3L73-0-00-501",
          "quantity": 1,
          "pickType": "Regular"
        },
        {
          "sku": "3227-101-D",
          "quantity": 3,
          "pickType": "Regular"
        },
        {
          "sku": "2087-0-00-300-S",
          "quantity": 2,
          "pickType": "Pick and Pack"
        },
        {
          "sku": "71071-0-00-300",
          "quantity": 1,
          "pickType": "Pick and Pack"
        },
        {
          "sku": "2R73-R-0-700-R",
          "quantity": 1,
          "pickType": "Pick and Pack"
        },
        {
          "sku": "70073-0-00-801",
          "quantity": 1,
          "pickType": "Pick and Pack"
        },
        {
          "sku": "2+2+2089-L-00-300-S-D",
          "quantity": 1,
          "pickType": "Pick and Pack"
        }
      ]
    },
    {
      "orderType": "regular-only",
      "customer": {
        "name": "Test Customer Windsor 2",
        "email": "test-windsor-2@example.com",
        "address": "1155 Lauzon Road",
        "city": "Windsor",
        "province": "ON",
        "postalCode": "N8S 3N1"
      },
      "lineItems": [
        {
          "sku": "2+3L73-0-00-501",
          "quantity": 2,
          "pickType": "Regular"
        },
        {
          "sku": "2208-202-R",
          "quantity": 1,
          "pickType": "Regular"
        },
        {
          "sku": "2+2+2089-R-00-300-S",
          "quantity": 2,
          "pickType": "Regular"
        },
        {
          "sku": "2+2+2244-301",
          "quantity": 10,
          "pickType": "Regular"
        }
      ]
    },
    {
      "orderType": "regular-only",
      "customer": {
        "name": "Test Customer Windsor 2",
        "email": "test-windsor-2@example.com",
        "address": "1155 Lauzon Road",
        "city": "Windsor",
        "province": "ON",
        "postalCode": "N8S 3N1"
      },
      "lineItems": [
        {
          "sku": "2+3+2234-112",
          "quantity": 17,
          "pickType": "Regular"
        },
        {
          "sku": "3+3278-201-R",
          "quantity": 2,
          "pickType": "Regular"
        },
        {
          "sku": "20063-112-1",
          "quantity": 4,
          "pickType": "Regular"
        },
        {
          "sku": "34004-1-50-9x12C",
          "quantity": 1,
          "pickType": "Regular"
        },
        {
          "sku": "2+3+2L70-0-00-300-S",
          "quantity": 1,
          "pickType": "Regular"
        },
        {
          "sku": "2+3+2337-111",
          "quantity": 2,
          "pickType": "Regular"
        },
        {
          "sku": "42024-101-2x1-R",
          "quantity": 2,
          "pickType": "Regular"
        },
        {
          "sku": "1036-111-R",
          "quantity": 14,
          "pickType": "Regular"
        }
      ]
    },
    {
      "orderType": "pnp-only",
      "customer": {
        "name": "Test Customer Windsor 1",
        "email": "test-windsor-1@example.com",
        "address": "350 City Hall Square West",
        "city": "Windsor",
        "province": "ON",
        "postalCode": "N9A 6S1"
      },
      "lineItems": [
        {
          "sku": "4R73-R-0-710-R",
          "quantity": 2,
          "pickType": "Pick and Pack"
        },
        {
          "sku": "25000-202",
          "quantity": 1,
          "pickType": "Pick and Pack"
        }
      ]
    },
    {
      "orderType": "pnp-only",
      "customer": {
        "name": "Test Customer Windsor 2",
        "email": "test-windsor-2@example.com",
        "address": "1155 Lauzon Road",
        "city": "Windsor",
        "province": "ON",
        "postalCode": "N8S 3N1"
      },
      "lineItems": [
        {
          "sku": "30002-351-R",
          "quantity": 8,
          "pickType": "Pick and Pack"
        },
        {
          "sku": "20078-204-R",
          "quantity": 1,
          "pickType": "Pick and Pack"
        },
        {
          "sku": "2058-0-00-300-S-D",
          "quantity": 4,
          "pickType": "Pick and Pack"
        }
      ]
    },
    {
      "orderType": "mixed",
      "customer": {
        "name": "Test Customer Windsor 2",
        "email": "test-windsor-2@example.com",
        "address": "1155 Lauzon Road",
        "city": "Windsor",
        "province": "ON",
        "postalCode": "N8S 3N1"
      },
      "lineItems": [
        {
          "sku": "3226-102-R",
          "quantity": 1,
          "pickType": "Regular"
        },
        {
          "sku": "46K73-S-UU-N-S-2-100-D",
          "quantity": 1,
          "pickType": "Regular"
        },
        {
          "sku": "2+2+2137-111-D",
          "quantity": 2,
          "pickType": "Regular"
        },
        {
          "sku": "2+3271-2A1-D",
          "quantity": 5,
          "pickType": "Regular"
        },
        {
          "sku": "2+1L89-0-00-300-S-D",
          "quantity": 2,
          "pickType": "Regular"
        },
        {
          "sku": "2041-2-00-300-S-R",
          "quantity": 4,
          "pickType": "Pick and Pack"
        },
        {
          "sku": "700-100-0-00-121-R",
          "quantity": 2,
          "pickType": "Pick and Pack"
        },
        {
          "sku": "70048-0-00-300-R",
          "quantity": 2,
          "pickType": "Pick and Pack"
        },
        {
          "sku": "74048-301-1",
          "quantity": 1,
          "pickType": "Pick and Pack"
        },
        {
          "sku": "20031-103-1",
          "quantity": 2,
          "pickType": "Pick and Pack"
        }
      ]
    },
    {
      "orderType": "mixed",
      "customer": {
        "name": "Test Customer Langley 2",
        "email": "test-langley-2@example.com",
        "address": "13737 96 Avenue",
        "city": "Surrey",
        "province": "BC",
        "postalCode": "V3V 0C6"
      },
      "lineItems": [
        {
          "sku": "2+2+2078-0-00-5A1",
          "quantity": 1,
          "pickType": "Regular"
        },
        {
          "sku": "2+3+2201-2A1",
          "quantity": 1,
          "pickType": "Regular"
        },
        {
          "sku": "13089-0-00-300-S-D",
          "quantity": 8,
          "pickType": "Regular"
        },
        {
          "sku": "2+3016-0-2-701",
          "quantity": 1,
          "pickType": "Pick and Pack"
        },
        {
          "sku": "46F73-R-U0-N-0-0-101-D",
          "quantity": 9,
          "pickType": "Pick and Pack"
        },
        {
          "sku": "20028-104-1",
          "quantity": 1,
          "pickType": "Pick and Pack"
        },
        {
          "sku": "70089-E-00-300",
          "quantity": 2,
          "pickType": "Pick and Pack"
        }
      ]
    },
    {
      "orderType": "mixed",
      "customer": {
        "name": "Test Customer Windsor 1",
        "email": "test-windsor-1@example.com",
        "address": "350 City Hall Square West",
        "city": "Windsor",
        "province": "ON",
        "postalCode": "N9A 6S1"
      },
      "lineItems": [
        {
          "sku": "2+3+2049-0-00-300-S-R",
          "quantity": 5,
          "pickType": "Regular"
        },
        {
          "sku": "2+2+2069-L-00-300-S-R",
          "quantity": 1,
          "pickType": "Regular"
        },
        {
          "sku": "3+3R47-0-00-300",
          "quantity": 1,
          "pickType": "Regular"
        },
        {
          "sku": "71056-0-00-302-S-D",
          "quantity": 1,
          "pickType": "Pick and Pack"
        },
        {
          "sku": "3R19-0-0-701-R",
          "quantity": 2,
          "pickType": "Pick and Pack"
        },
        {
          "sku": "11059-E-00-300-S",
          "quantity": 9,
          "pickType": "Pick and Pack"
        },
        {
          "sku": "4052-L-00-300",
          "quantity": 1,
          "pickType": "Pick and Pack"
        }
      ]
    },
    {
      "orderType": "mixed",
      "customer": {
        "name": "Test Customer Royalmount 2",
        "email": "test-royalmount-2@example.com",
        "address": "1250 Boulevard René-Lévesque Ouest",
        "city": "Montreal",
        "province": "QC",
        "postalCode": "H3B 4W8"
      },
      "lineItems": [
        {
          "sku": "2+2L18-R-00-501",
          "quantity": 3,
          "pickType": "Regular"
        },
        {
          "sku": "70050-0-00-301",
          "quantity": 2,
          "pickType": "Pick and Pack"
        },
        {
          "sku": "4L16-0-0-710-R",
          "quantity": 4,
          "pickType": "Pick and Pack"
        }
      ]
    }
  ]
}
